kuest_py_order_utils-0.3.3.dist-info/licenses/LICENSE
py_order_utils/__init__.py
py_order_utils/constants.py
py_order_utils/signer.py
py_order_utils/utils.py
py_order_utils/abi/Exchange.json
py_order_utils/builders/__init__.py
py_order_utils/builders/base_builder.py
py_order_utils/builders/exception.py
py_order_utils/builders/order_builder.py
py_order_utils/model/__init__.py
py_order_utils/model/order.py
py_order_utils/model/sides.py
py_order_utils/model/signatures.py
tests/__init__.py
tests/test_order_builder.py
tests/test_utils.py
kuest_py_order_utils-0.3.3.dist-info/METADATA
kuest_py_order_utils-0.3.3.dist-info/WHEEL
kuest_py_order_utils-0.3.3.dist-info/top_level.txt
kuest_py_order_utils-0.3.3.dist-info/RECORD
