Metadata-Version: 2.4
Name: kuest-py-order-utils
Version: 0.3.3
Summary: Python utilities used to generate and sign orders for the Kuest CTF Exchange
Home-page: https://github.com/kuestcom/py-order-utils
Author: Kuest Engineering
Author-email: engineering@kuest.com
Maintainer: Kuest Engineering
Maintainer-email: engineering@kuest.com
Project-URL: Bug Tracker, https://github.com/kuestcom/py-order-utils/issues
Classifier: Programming Language :: Python :: 3
Classifier: License :: OSI Approved :: MIT License
Classifier: Operating System :: OS Independent
Requires-Python: >=3.9.10
License-File: LICENSE
Requires-Dist: eth-utils>=4.1.1
Requires-Dist: eth-account>=0.13.0
Requires-Dist: kuest-py-eip712-structs==0.0.2
Requires-Dist: pytest
Dynamic: author
Dynamic: author-email
Dynamic: classifier
Dynamic: description
Dynamic: description-content-type
Dynamic: home-page
Dynamic: license-file
Dynamic: maintainer
Dynamic: maintainer-email
Dynamic: project-url
Dynamic: requires-dist
Dynamic: requires-python
Dynamic: summary
